README.md
setup.py
LePoop.egg-info/PKG-INFO
LePoop.egg-info/SOURCES.txt
LePoop.egg-info/dependency_links.txt
LePoop.egg-info/entry_points.txt
LePoop.egg-info/not-zip-safe
LePoop.egg-info/requires.txt
LePoop.egg-info/top_level.txt
lepoop/__init__.py
lepoop/download.py
lepoop/install.py
lepoop/uninstall.py
lepoop/utils.py
lepoop/entry/__init__.py
lepoop/entry/alias.py
lepoop/entry/main.py
lepoop/entry/not_configured.py