Metadata-Version: 1.1
Name: LePoop
Version: 0.1.2
Summary: Allows you to undo pip commands
Home-page: https://github.com/alvinwan/lepoop
Author: Alvin Wan
Author-email: hi@alvinwan.com
License: BSD
Download-URL: https://github.com/alvinwan/lepoop/archive/0.1.2.zip
Platform: UNKNOWN
Classifier: Topic :: Utilities
Classifier: Intended Audience :: Developers
Classifier: Programming Language :: Python :: 3
Classifier: Topic :: Software Development :: Libraries
